cqml/__init__.py
cqml/boxquilt.py
cqml/cvm.py
cqml/db2quilt.py
cqml/helpers.py
cqml/keys.py
cqml/vm.py
cqml/wrappers.py
cqml-0.4.5.dist-info/LICENSE
cqml-0.4.5.dist-info/METADATA
cqml-0.4.5.dist-info/WHEEL
cqml-0.4.5.dist-info/top_level.txt
cqml-0.4.5.dist-info/RECORD
