Metadata-Version: 2.1
Name: cqml
Version: 0.4.5
Summary: Composable Query Meta Language
Home-page: https://github.com/TheSwanFactory/cqml
Author: Ernest Prabhakar
Author-email: ernest.prabhakar@gmail.com
Project-URL: Bug Tracker, https://github.com/TheSwanFactory/cqml/issues
Classifier: Programming Language :: Python :: 3
Classifier: License :: OSI Approved :: MIT License
Classifier: Operating System :: OS Independent
Requires-Python: >=3.6
License-File: LICENSE
Requires-Dist: nbformat
Requires-Dist: pandas
Requires-Dist: pyspark
Requires-Dist: pytz
Requires-Dist: quilt3
Requires-Dist: boxsdk
Requires-Dist: boxsdk[jwt]
Requires-Dist: dbl-tempo
